[
    {
        "title": "優勢策略",
        "keyword": [
            "優勢策略",
            "優勢策略是什麼",
            "優勢策略意思",
            "優勢策略解釋"
        ],
        "answer": [
            "優勢策略：指的是在賽局中，無論其他參與者選擇什麼策略，該策略都能為選擇它的參與者帶來最好的結果"
        ]
    },
    {
        "title": "限制轉售價格",
        "keyword": [
            "限制轉售價格",
            "限制轉售價格是什麼",
            "限制轉售價格意思",
            "限制轉售價格解釋"
        ],
        "answer": [
            "限制轉售價格：指的是製造商或供應商要求其經銷商或零售商以指定價格出售產品，而不是由零售商自行決定價格",
            "主要目標:維持品牌形象、保護零售商、確保服務質量"
        ]
    },
    {
        "title": "流動性偏好理論",
        "keyword": [
            "流動性偏好理論",
            "流動性偏好理論是什麼",
            "流動性偏好理論意思",
            "流動性偏好理論解釋"
        ],
        "answer": [
            "流動性偏好理論：由英國經濟學家約翰·梅納德·凱恩斯（John Maynard Keynes）提出的，主張利率會調整至使貨幣供需達成平衡，利率是由貨幣的供給與需求決定的，而貨幣需求則受到人們的流動性偏好的影響",
            "https://miro.medium.com/v2/resize:fit:1100/format:webp/1*U5sj8N9cUrrOSr-NlPalsA.png",
            "https://miro.medium.com/v2/resize:fit:1100/format:webp/1*iOnwA2XooHGxbhAZMh8-Tg.png"
        ]
    },
    {
        "title": "流動性陷阱",
        "keyword": [
            "流動性陷阱",
            "流動性陷阱是什麼",
            "流動性陷阱意思",
            "流動性陷阱解釋"
        ],
        "answer": [
            "流動性陷阱：指的是利率接近零或極低的情況下，貨幣政策失去效力，無法透過進一步降低利率來刺激經濟成長，無論中央銀行如何增加貨幣供給量，經濟主體（如企業和消費者）都不會增加投資和消費，導致貨幣政策陷入無效狀態",
            "ex:日本經濟泡沫化、全球金融危機等等"
        ]
    },
    {
        "title": "前瞻引導",
        "keyword": [
            "前瞻引導",
            "前瞻引導是什麼",
            "前瞻引導意思",
            "前瞻引導解釋"
        ],
        "answer": [
            "前瞻引導：要透過中央銀行對未來貨幣政策方向的公開溝通，影響市場預期和經濟主體的行為，旨在提供透明度和確定性，幫助市場參與者做出更合理的決策，進而增強貨幣政策的效果",
            "例如: \n 中央銀行承諾未來貨幣供給成長，提高人們預期物價膨脹，意味著實質利率為負值，進而刺激投資支出"
        ]
    },
    {
        "title": "投資的加速原理",
        "keyword": [
            "投資的加速原理",
            "投資的加速原理是什麼",
            "投資的加速原理意思",
            "投資的加速原理解釋",
            "加速原理",
            "加速原理是什麼"
        ],
        "answer": [
            "投資的加速原理：當經濟活動增加時，企業預期未來需求會上升，因此需要增加資本存量（如機器設備、工廠等）以滿足未來的生產需求",
            "例如: \n 政府可以利用加速原理，透過刺激總需求（如增加政府支出或減稅）來間接促進企業投資，推動經濟成長"
        ]
    },
    {
        "title": "邊際儲蓄傾向",
        "keyword": [
            "邊際儲蓄傾向",
            "邊際儲蓄傾向是什麼",
            "邊際儲蓄傾向意思",
            "邊際儲蓄傾向解釋"
        ],
        "answer": [
            "指收入中每增加一單位，消費者用於儲蓄的部分，MPS 反映了儲蓄對收入變化的敏感度，通常和邊際消費傾向（MPC）一起使用來分析消費者的儲蓄和消費行為",
            "MPS 的值介於 0 和 1 之間，MPS 等於 0 表示新增收入完全用於消費，MPS 等於 1 表示新增收入全部用於儲蓄"
        ]
    },
    {
        "title": "排擠效果",
        "keyword": [
            "排擠效果",
            "排擠效果是什麼",
            "排擠效果意思",
            "排擠效果解釋"
        ],
        "answer": [
            "排擠效果：指政府增加支出或擴大財政赤字所造成的利率上升，從而減少了私部門的投資支出，特別是在討論財政政策和貨幣政策的相互作用時",
            "類型:完全排擠、部分排擠、無排擠"
        ]
    },
    {
        "title": "自動穩定因子",
        "keyword": [
            "自動穩定因子",
            "自動穩定因子是什麼",
            "自動穩定因子意思",
            "自動穩定因子解釋",
            "automatic stabilizers"
        ],
        "answer": [
            "自動穩定因子：旨在在不需直接干預的情況下抵消經濟活動的波動，特別是在經濟衰退或蕭條期間，有助於穩定總合需求，平滑經濟周期，財政政策的自動變化",
            "例子:失業救濟、企業利潤稅等等"
        ]
    },
    {
        "title": "總合需求線",
        "keyword": [
            "總合需求線",
            "總合需求曲線",
            "總合需求曲線是什麼",
            "總合需求曲線意思",
            "總合需求曲線解釋",
            "甚麼是總合需求線",
            "什麼是總合需求線"
        ],
        "answer": [
            "總合需求線：在每一物價水準下，家戶、廠商、政府、國外顧客想要購買本國商品與服務數量的曲線",
            "當物價下跌商品與服務需求量增加原因: \n\n 消費者變得富有使消費財需求量增加 \n 利率下跌使投資才需求量增加 \n 實質匯率下跌使出口淨額增加",
            "https://miro.medium.com/v2/resize:fit:1100/format:webp/1*kpVqrhLZ7lkZp2cyYJIERA.png",
            "https://miro.medium.com/v2/resize:fit:1100/format:webp/1*9xLR8H4GhAs_ly0MOdHoeA.png"
        ]
    },
    {
        "title": "總合供給線",
        "keyword": [
            "總合供給線",
            "總合供給曲線",
            "總合供給曲線是什麼",
            "總合供給曲線意思",
            "總合供給曲線解釋",
            "什麼是總合供給線",
            "甚麼是總合供給線"
        ],
        "answer": [
            "總合供給線：在每一物價水準下，本國廠商生產的商品與服務數量的曲線，而長期的總合供給曲線是呈現垂直",
            "https://miro.medium.com/v2/resize:fit:1100/format:webp/1*vB1B4baVkYef8Ardunkgqw.png",
            "https://miro.medium.com/v2/resize:fit:1100/format:webp/1*9xLR8H4GhAs_ly0MOdHoeA.png"
        ]
    },
    {
        "title": "排擠",
        "keyword": [
            "排擠",
            "排擠是什麼",
            "排擠意思",
            "排擠解釋"
        ],
        "answer": [
            "排擠：通常指的是政府支出增加導致私人部門投資或消費減少的現象",
            "排擠效應強調了在制定經濟政策時需要考慮的財政和貨幣政策的相互作用"
        ]
    },
    {
        "title": "擁擠效應",
        "keyword": [
            "擁擠效應",
            "擁擠效應是什麼",
            "擁擠效應意思",
            "擁擠效應解釋"
        ],
        "answer": [
            "擁擠效應：指在某些情況下，政府支出或其他外部因素的增加會導致私人投資或消費支出的減少",
            "例如: \n 如果政府決定大規模建設道路或橋樑，這可能會推高建材和工人的價格，使得私人企業的建設成本增加，進而減少他們的投資"
        ]
    },
    {
        "title": "一籃通貨",
        "keyword": [
            "一籃通貨",
            "一籃通貨是什麼",
            "一籃通貨意思",
            "一籃通貨解釋"
        ],
        "answer": [
            "一籃通貨：將多種貨幣集合在一起形成一個通貨指標或參考標準，主要用於衡量貨幣的價值、設置貨幣政策、以及進行國際比較",
            "例如: \n 美元指數是一個基於美元對六種主要貨幣（歐元、日元、英鎊、加元、瑞典克朗和瑞士法郎）的一籃指數"
        ]
    }
]